aiv/AIV.py
aiv/__init__.py
aiv-0.4.3.dist-info/LICENSE.txt
aiv-0.4.3.dist-info/METADATA
aiv-0.4.3.dist-info/WHEEL
aiv-0.4.3.dist-info/top_level.txt
aiv-0.4.3.dist-info/RECORD
