Metadata-Version: 2.1
Name: aiv
Version: 0.4.3
Summary: A variant annotation package
Home-page: https://github.com/nesegunes/aiv
Author: tardis
Author-email: nesegunes.ce@gmail.com
License: UNKNOWN
Platform: UNKNOWN
Classifier: Programming Language :: Python :: 3.6
Classifier: Programming Language :: Python :: 3.7
Classifier: Programming Language :: Python :: 3.8
Classifier: License :: OSI Approved :: MIT License
Classifier: Operating System :: OS Independent
Requires-Python: >=3.6
Requires-Dist: myvariant
Requires-Dist: pandas
Requires-Dist: reportlab
